backend/__init__.py
frontend/__init__.py
frontend/_validate_init.py
frontend/setup.py
frontend/usage.py
frontend/viasp_dash/__init__.py
frontend/viasp_dash/_imports_.py
frontend/viasp_dash/react_server.py
viasp-2.3.0.post3.dist-info/licenses/LICENCE.md
viasp-2.3.0.post3.dist-info/METADATA
viasp-2.3.0.post3.dist-info/WHEEL
viasp-2.3.0.post3.dist-info/top_level.txt
viasp-2.3.0.post3.dist-info/RECORD
