Metadata-Version: 2.4
Name: viasp
Version: 2.3.0.post3
Summary: a visualization tool for clingo.
Home-page: https://github.com/potassco/viasp
Author: Luis Glaser
Author-email: Luis.Glaser@uni-potsdam.de
License: MIT
Classifier: License :: OSI Approved :: MIT License
Classifier: Programming Language :: Python
Classifier: Programming Language :: Python :: 3
Classifier: Programming Language :: Python :: 3.6
Classifier: Programming Language :: Python :: Implementation :: CPython
Classifier: Programming Language :: Python :: Implementation :: PyPy
Requires-Python: >=3.8.0
License-File: LICENCE.md
Requires-Dist: viasp-backend
Requires-Dist: viasp-dash
Requires-Dist: jupyter-server-proxy
Requires-Dist: clingraph
Requires-Dist: graphviz
Dynamic: author
Dynamic: author-email
Dynamic: classifier
Dynamic: description
Dynamic: description-content-type
Dynamic: home-page
Dynamic: license
Dynamic: license-file
Dynamic: requires-dist
Dynamic: requires-python
Dynamic: summary
